remu/__init__.py
remu/_version.py
remu/binning.py
remu/likelihood.py
remu/likelihood_utils.py
remu/matrix_utils.py
remu/migration.py
remu/plotting.py
remu-0.8.0.dist-info/LICENSE
remu-0.8.0.dist-info/METADATA
remu-0.8.0.dist-info/WHEEL
remu-0.8.0.dist-info/top_level.txt
remu-0.8.0.dist-info/RECORD
