Metadata-Version: 2.1
Name: remu
Version: 0.8.0
Summary: Response Matrix Utilities for likelihood calculations and hypothesis testing
Author-email: Lukas Koch <lukas.koch@mailbox.org>
License: MIT License
Project-URL: Home, https://remu.readthedocs.io/en/latest/
Classifier: Development Status :: 4 - Beta
Classifier: Intended Audience :: Developers
Classifier: Intended Audience :: Science/Research
Classifier: Topic :: Scientific/Engineering
Classifier: License :: OSI Approved :: MIT License
Classifier: Programming Language :: Python :: 3
Classifier: Programming Language :: Python :: 3.7
Classifier: Programming Language :: Python :: 3.8
Classifier: Programming Language :: Python :: 3.9
Classifier: Programming Language :: Python :: 3.10
Classifier: Programming Language :: Python :: 3.11
Requires-Python: <4,>=3.7
License-File: LICENSE
Requires-Dist: numpy (>=1.21.0)
Requires-Dist: scipy (>=1.7.0)
Requires-Dist: pyyaml (>=5.4)
Requires-Dist: matplotlib (>=3.5.0)
Provides-Extra: mcmc
Requires-Dist: emcee (>=3.1.0) ; extra == 'mcmc'
